cascade/__init__.py
cascade/py.typed
cascade/benchmarks/__init__.py
cascade/benchmarks/__main__.py
cascade/benchmarks/anemoi.py
cascade/benchmarks/dask.py
cascade/benchmarks/dist.py
cascade/benchmarks/generators.py
cascade/benchmarks/job1.py
cascade/benchmarks/matmul.py
cascade/benchmarks/plotting.py
cascade/benchmarks/reporting.py
cascade/benchmarks/tests.py
cascade/benchmarks/util.py
cascade/controller/__init__.py
cascade/controller/act.py
cascade/controller/core.py
cascade/controller/impl.py
cascade/controller/notify.py
cascade/controller/report.py
cascade/executor/bridge.py
cascade/executor/comms.py
cascade/executor/config.py
cascade/executor/data_server.py
cascade/executor/executor.py
cascade/executor/msg.py
cascade/executor/platform.py
cascade/executor/serde.py
cascade/executor/runner/__init__.py
cascade/executor/runner/entrypoint.py
cascade/executor/runner/memory.py
cascade/executor/runner/packages.py
cascade/executor/runner/runner.py
cascade/gateway/__init__.py
cascade/gateway/__main__.py
cascade/gateway/api.py
cascade/gateway/client.py
cascade/gateway/router.py
cascade/gateway/server.py
cascade/low/__init__.py
cascade/low/builders.py
cascade/low/core.py
cascade/low/dask.py
cascade/low/execution_context.py
cascade/low/func.py
cascade/low/into.py
cascade/low/tracing.py
cascade/low/views.py
cascade/scheduler/__init__.py
cascade/scheduler/api.py
cascade/scheduler/assign.py
cascade/scheduler/core.py
cascade/scheduler/precompute.py
cascade/shm/__init__.py
cascade/shm/algorithms.py
cascade/shm/api.py
cascade/shm/client.py
cascade/shm/dataset.py
cascade/shm/disk.py
cascade/shm/func.py
cascade/shm/server.py
earthkit/workflows/__init__.py
earthkit/workflows/_version.py
earthkit/workflows/decorators.py
earthkit/workflows/fluent.py
earthkit/workflows/mark.py
earthkit/workflows/taskgraph.py
earthkit/workflows/transformers.py
earthkit/workflows/utility.py
earthkit/workflows/visualise.py
earthkit/workflows/backends/__init__.py
earthkit/workflows/backends/arrayapi.py
earthkit_workflows-0.5.1.dist-info/licenses/LICENSE
earthkit_workflows-0.5.1.dist-info/METADATA
earthkit_workflows-0.5.1.dist-info/WHEEL
earthkit_workflows-0.5.1.dist-info/top_level.txt
earthkit_workflows-0.5.1.dist-info/RECORD
